auth/__init__.py
auth/users/__init__.py
auth/users/admin.py
auth/users/models.py
auth/users/serializers.py
auth/users/tests.py
auth/users/urls.py
auth/users/views.py
drf_authentication_with_knox-0.0.1.dist-info/LICENSE
drf_authentication_with_knox-0.0.1.dist-info/METADATA
drf_authentication_with_knox-0.0.1.dist-info/WHEEL
drf_authentication_with_knox-0.0.1.dist-info/top_level.txt
drf_authentication_with_knox-0.0.1.dist-info/RECORD
