Metadata-Version: 2.1
Name: drf-authentication-with-knox
Version: 0.0.1
Summary: For drf simple authentication with custom user model
Home-page: https://github.com/degerahmet/
Author: Ahmet Deger
Author-email: adeger@protonmail.com
License: Apache Software License
Platform: UNKNOWN
Classifier: Programming Language :: Python :: 3
Classifier: License :: OSI Approved :: Apache Software License
Classifier: Operating System :: OS Independent
Requires-Python: >=3.5
License-File: LICENSE
Requires-Dist: knox
Requires-Dist: rest-framework-simplejwt
Requires-Dist: jwt
Requires-Dist: datetime
